linkedin_influencer_mcp/__init__.py
linkedin_influencer_mcp/main.py
linkedin_influencer_mcp/browser/__init__.py
linkedin_influencer_mcp/browser/browser.py
linkedin_influencer_mcp/browser/feed_page.py
linkedin_influencer_mcp/browser/login_page.py
linkedin_influencer_mcp/browser/profile_page.py
linkedin_influencer_mcp/browser/recent_activity_page.py
linkedin_influencer_mcp/browser/search_page/__init__.py
linkedin_influencer_mcp/browser/search_page/search_page.py
linkedin_influencer_mcp/browser/search_page/search_page_helpers.py
linkedin_influencer_mcp/browser/utils/__init__.py
linkedin_influencer_mcp/browser/utils/dependencies.py
linkedin_influencer_mcp/browser/utils/utils.py
linkedin_influencer_mcp/models/__init__.py
linkedin_influencer_mcp-0.1.7.dist-info/METADATA
linkedin_influencer_mcp-0.1.7.dist-info/WHEEL
linkedin_influencer_mcp-0.1.7.dist-info/entry_points.txt
linkedin_influencer_mcp-0.1.7.dist-info/top_level.txt
linkedin_influencer_mcp-0.1.7.dist-info/RECORD
