Metadata-Version: 2.2
Name: linkedin_influencer_mcp
Version: 0.1.7
Summary: LinkedIn influencer automation with MCP
Author-email: Shrey Shah <ssshrey@gmail.com>
License: MIT
Keywords: linkedin,automation,influencer,mcp
Classifier: Development Status :: 3 - Alpha
Classifier: Intended Audience :: Developers
Classifier: License :: OSI Approved :: MIT License
Classifier: Programming Language :: Python :: 3
Classifier: Programming Language :: Python :: 3.10
Requires-Python: >=3.10
Requires-Dist: openai>=1.0.0
Requires-Dist: python-dotenv>=1.0.1
Requires-Dist: requests>=2.31.0
Requires-Dist: linkedin-api>=2.0.0
Requires-Dist: fastmcp>=0.4.1
Requires-Dist: playwright>=1.49.1
Requires-Dist: beautifulsoup4>=4.12.3
Requires-Dist: bs4>=0.0.2
Requires-Dist: lxml>=4.9.0
Requires-Dist: mcp[cli]>=1.0.0
Requires-Dist: langchain_groq>=0.1.0
Requires-Dist: pydantic>=2.10.6
Requires-Dist: uvicorn>=0.24.0
Requires-Dist: langchain_google_genai>=0.0.1
Requires-Dist: langchain_openai>=0.0.1
Requires-Dist: langchain_core
Requires-Dist: langchain_community
Provides-Extra: dev
Requires-Dist: mypy>=1.7.0; extra == "dev"
Requires-Dist: ruff>=0.1.6; extra == "dev"
Requires-Dist: black>=24.1.1; extra == "dev"
Requires-Dist: flake8>=7.0.0; extra == "dev"
Requires-Dist: isort>=5.13.2; extra == "dev"
Requires-Dist: pre-commit>=3.6.0; extra == "dev"
Provides-Extra: test
Requires-Dist: pytest>=8.3.4; extra == "test"
Requires-Dist: pytest-cov>=4.1.0; extra == "test"
Requires-Dist: pytest-asyncio>=0.23.5; extra == "test"
